ILAMB/ConfAlbedo.py
ILAMB/ConfBasin.py
ILAMB/ConfBurntArea.py
ILAMB/ConfCO2.py
ILAMB/ConfContentChange.py
ILAMB/ConfDepthGradient.py
ILAMB/ConfDiurnal.py
ILAMB/ConfEvapFraction.py
ILAMB/ConfGSNF.py
ILAMB/ConfNBP.py
ILAMB/ConfPermafrost.py
ILAMB/ConfRunoff.py
ILAMB/ConfSWE.py
ILAMB/ConfSoilCarbon.py
ILAMB/ConfTWSA.py
ILAMB/ConfUSGS.py
ILAMB/ConfUncertainty.py
ILAMB/Confrontation.py
ILAMB/ModelResult.py
ILAMB/Post.py
ILAMB/Regions.py
ILAMB/Relationship.py
ILAMB/Scoreboard.py
ILAMB/Variable.py
ILAMB/__init__.py
ILAMB/ccgfilt.py
ILAMB/constants.py
ILAMB/e3sm_result.py
ILAMB/generated_version.py
ILAMB/ilamblib.py
ILAMB/point_result.py
ILAMB/run.py
ILAMB/data/cmip.cfg
ILAMB/data/diurnal.cfg
ILAMB/data/ilamb.cfg
ILAMB/data/ilamb_nohoff_final_CLM.cfg
ILAMB/data/ilamb_nohoff_final_CLM_SP.cfg
ILAMB/data/iomb.cfg
ILAMB/data/quantiles_Whittaker_cmip5v6.parquet
ILAMB/data/sample.cfg
ilamb-2.7.3.data/scripts/ilamb-fetch
ilamb-2.7.3.data/scripts/ilamb-mean
ilamb-2.7.3.data/scripts/ilamb-run
ilamb-2.7.3.data/scripts/ilamb-setup
ilamb-2.7.3.dist-info/licenses/LICENSE.rst
ilamb-2.7.3.dist-info/METADATA
ilamb-2.7.3.dist-info/WHEEL
ilamb-2.7.3.dist-info/top_level.txt
ilamb-2.7.3.dist-info/RECORD
