Metadata-Version: 2.4
Name: ILAMB
Version: 2.7.3
Summary: The International Land Model Benchmarking Package
Home-page: https://github.com/rubisco-sfa/ILAMB.git
Author: Nathan Collier
Author-email: nathaniel.collier@gmail.com
License: BSD-3-Clause
Keywords: benchmarking,earth system modeling,climate modeling,model intercomparison
Classifier: Development Status :: 5 - Production/Stable
Classifier: Intended Audience :: Science/Research
Classifier: Topic :: Scientific/Engineering
Classifier: License :: OSI Approved :: BSD License
Classifier: Operating System :: MacOS
Classifier: Operating System :: POSIX
Classifier: Operating System :: POSIX :: Linux
Classifier: Programming Language :: Python :: 3
License-File: LICENSE.rst
Requires-Dist: numpy
Requires-Dist: pandas
Requires-Dist: matplotlib
Requires-Dist: cartopy
Requires-Dist: netCDF4
Requires-Dist: cf-units
Requires-Dist: sympy
Requires-Dist: mpi4py
Requires-Dist: scipy
Requires-Dist: cftime
Requires-Dist: tqdm
Requires-Dist: pyarrow
Requires-Dist: pyyaml
Requires-Dist: requests
Provides-Extra: watershed
Requires-Dist: contextily; extra == "watershed"
Requires-Dist: geopandas; extra == "watershed"
Requires-Dist: dataretrieval; extra == "watershed"
Requires-Dist: pynhd; extra == "watershed"
Dynamic: author
Dynamic: author-email
Dynamic: classifier
Dynamic: description
Dynamic: home-page
Dynamic: keywords
Dynamic: license
Dynamic: license-file
Dynamic: provides-extra
Dynamic: requires-dist
Dynamic: summary
